<?xml version="1.0" encoding="utf-8"?><?workdir /Users/jelovirt/Work/SF/dita-ot/temp/conref/preprocess?><?path2project?><?Pub Inc?><task xmlns:ditaarch="http://dita.oasis-open.org/architecture/2005/" id="taskforrelatedlink" xml:lang="en-us" ditaarch:DITAArchVersion="1.2" domains="(topic task)                            (topic hi-d)                             (topic ut-d)                             (topic indexing-d)                            (topic hazard-d)                            (topic abbrev-d)                            (topic pr-d)                             (topic sw-d)                            (topic ui-d)                            (topic task strictTaskbody-c)    " class="- topic/topic task/task " xtrf="/Users/jelovirt/Work/SF/testsuite/testcase/conref/src/lang-task.dita" xtrc="task:1">
<title class="- topic/title " xtrf="/Users/jelovirt/Work/SF/testsuite/testcase/conref/src/lang-task.dita" xtrc="title:1">Task for related link</title>
<shortdesc class="- topic/shortdesc " xtrf="/Users/jelovirt/Work/SF/testsuite/testcase/conref/src/lang-task.dita" xtrc="shortdesc:1">Description of the related task</shortdesc>
<taskbody class="- topic/body task/taskbody " xtrf="/Users/jelovirt/Work/SF/testsuite/testcase/conref/src/lang-task.dita" xtrc="taskbody:1">
<prereq class="- topic/section task/prereq " xtrf="/Users/jelovirt/Work/SF/testsuite/testcase/conref/src/lang-task.dita" xtrc="prereq:1">You need to do this first.</prereq>
</taskbody><?Pub Caret1?>
</task><?Pub *0000000412?>